{
  "$schema": "https://developer.microsoft.com/json-schemas/fabric/item/report/definition/visualContainer/2.4.0/schema.json",
  "name": "d84d7402067dd2fd7eed",
  "position": {
    "x": 658,
    "y": 452,
    "z": 15000,
    "height": 218,
    "width": 590,
    "tabOrder": 15000
  },
  "visual": {
    "visualType": "barChart",
    "query": {
      "queryState": {
        "Category": {
          "projections": [
            {
              "field": {
                "Column": {
                  "Expression": {
                    "SourceRef": {
                      "Entity": "Dim_TipoFormacion"
                    }
                  },
                  "Property": "TipoFormacion"
                }
              },
              "queryRef": "Dim_TipoFormacion.TipoFormacion",
              "nativeQueryRef": "TipoFormacion",
              "active": true
            }
          ]
        },
        "Y": {
          "projections": [
            {
              "field": {
                "Measure": {
                  "Expression": {
                    "SourceRef": {
                      "Entity": "Medidas_AD"
                    }
                  },
                  "Property": "Plan Actividades Ejecutadas"
                }
              },
              "queryRef": "Medidas_AD.Plan Actividades Ejecutadas",
              "nativeQueryRef": "Plan Actividades Ejecutadas"
            }
          ]
        }
      }
    },
    "drillFilterOtherVisuals": true,
    "visualContainerObjects": {
      "title": [
        {
          "properties": {
            "show": {
              "expr": {
                "Literal": {
                  "Value": "true"
                }
              }
            },
            "text": {
              "expr": {
                "Literal": {
                  "Value": "'Mix de ejecucion por tipo'"
                }
              }
            }
          }
        }
      ],
      "visualHeader": [
        {
          "properties": {
            "show": {
              "expr": {
                "Literal": {
                  "Value": "true"
                }
              }
            }
          }
        }
      ],
      "visualTooltip": [
        {
          "properties": {
            "show": {
              "expr": {
                "Literal": {
                  "Value": "true"
                }
              }
            }
          }
        }
      ]
    },
    "objects": {
      "labels": [
        {
          "properties": {
            "show": {
              "expr": {
                "Literal": {
                  "Value": "true"
                }
              }
            }
          }
        }
      ],
      "categoryAxis": [
        {
          "properties": {
            "showAxisTitle": {
              "expr": {
                "Literal": {
                  "Value": "false"
                }
              }
            }
          }
        }
      ],
      "valueAxis": [
        {
          "properties": {
            "showAxisTitle": {
              "expr": {
                "Literal": {
                  "Value": "false"
                }
              }
            }
          }
        }
      ],
      "legend": [
        {
          "properties": {
            "showTitle": {
              "expr": {
                "Literal": {
                  "Value": "false"
                }
              }
            }
          }
        }
      ]
    }
  }
}